{
  "parent": "minecraft:recipes/root",
  "criteria": {
    "has_steel_powder": {
      "conditions": {
        "items": [
          {
            "items": [
              "hexcraftmod:steel_powder"
            ]
          }
        ]
      },
      "trigger": "minecraft:inventory_changed"
    },
    "has_the_recipe": {
      "conditions": {
        "recipe": "hexcraftmod:steel_ingot_from_smelting_steel_powder"
      },
      "trigger": "minecraft:recipe_unlocked"
    }
  },
  "requirements": [
    [
      "has_steel_powder",
      "has_the_recipe"
    ]
  ],
  "rewards": {
    "recipes": [
      "hexcraftmod:steel_ingot_from_smelting_steel_powder"
    ]
  },
  "sends_telemetry_event": false
}